wwcpylib/__init__.py
wwcpylib/util.py
wwcpylib-0.0.4.dist-info/LICENSE
wwcpylib-0.0.4.dist-info/METADATA
wwcpylib-0.0.4.dist-info/WHEEL
wwcpylib-0.0.4.dist-info/top_level.txt
wwcpylib-0.0.4.dist-info/RECORD
