Metadata-Version: 2.1
Name: wwcpylib
Version: 0.0.4
Summary: More useful tools!
Home-page: https://github.com/iamwwc/wwcpylib
Author: iamwwc
Author-email: qaq1362211689@gmail.com
License: UNKNOWN
Platform: UNKNOWN
Classifier: Programming Language :: Python :: 3
Classifier: License :: OSI Approved :: MIT License
Classifier: Operating System :: OS Independent
Requires-Python: >=3.8
